listmonk_wrapper/__init__.py
listmonk_wrapper/client.py
listmonk_wrapper-0.1.3.dist-info/LICENSE
listmonk_wrapper-0.1.3.dist-info/WHEEL
listmonk_wrapper-0.1.3.dist-info/METADATA
listmonk_wrapper-0.1.3.dist-info/RECORD
